alslack/__init__.py
alslack/slack.py
alslack-0.1.dist-info/LICENSE.txt
alslack-0.1.dist-info/LICENSE.txt:Zone.Identifier
alslack-0.1.dist-info/METADATA
alslack-0.1.dist-info/WHEEL
alslack-0.1.dist-info/top_level.txt
alslack-0.1.dist-info/RECORD
